question_2/__init__.py
question_2/question2.py
question_package-0.1.dist-info/LICENSE
question_package-0.1.dist-info/METADATA
question_package-0.1.dist-info/WHEEL
question_package-0.1.dist-info/top_level.txt
question_package-0.1.dist-info/RECORD
