Metadata-Version: 2.1
Name: question-package
Version: 0.1
Author: Patrick Saade
Author-email: patrick_saade@hotmail.com
License: MIT
License-File: LICENSE
Requires-Dist: scikit-learn
Requires-Dist: numpy
